{
  "eyebrow": "Get In Touch",
  "headline": "Let's Craft Something Beautiful Together",
  "subheadline": "Tell us about the moment, the person, the dream. We will design the gift around it.",
  "whatsapp": "+91 98765 43210",
  "whatsappNumber": "919876543210",
  "instagram": "@elarose.gifts",
  "instagramUrl": "https://instagram.com/elarose.gifts",
  "email": "hello@elarose.in",
  "hours": "Mon–Sat · 10:00 AM – 7:00 PM",
  "formHeading": "Send a Custom Order",
  "formSubheading": "Fill in your details — on submit we'll open WhatsApp with your message ready.",
  "formCta": "Send via WhatsApp",
  "formNote": "On submit, WhatsApp will open with your message ready to send."
}
